Workbook
Name Salestable: 'Sales Data'!$A$1:$O$1001
Name Slicer_Payment_Mode: #N/A
Name Slicer_Product: #N/A
Name Slicer_Region: #N/A
Name Slicer_Years__Date: #N/A

Sheet Sales Data
A1: Order ID | B1: Date | C1: Customer Name | D1: Region | E1: State | F1: City | G1: Product Category | H1: Product | I1: Quantity | J1: Unit Cost | K1: Total Cost | L1: Sales Amount | M1: Profit | N1: Sales Category | O1: Payment Mode
A2: ORD01 | B2: 45293 | C2: Customer_40 | D2: North | E2: Uttar Pradesh | F2: Lucknow | G2: Electronics | H2: Tablet | I2: 4 | J2: 162 | K2: =J2*I2 -> 648 | L2: 757.87 | M2: =L2-K2 -> 109.87 | N2: {=IF(L2:L1001>2000,"High","Low")} -> Low | O2: UPI
A3: ORD02 | B3: 45294 | C3: Customer_191 | D3: North | E3: Madhya Pradesh | F3: Indore | G3: Electronics | H3: Accessories | I3: 8 | J3: 362.93 | K3: =J3*I3 -> 2903.44 | L3: 3439.63 | M3: =L3-K3 -> 536.19 | N3: High | O3: Cash
A4: ORD03 | B4: 45295 | C4: Customer_29 | D4: East | E4: Bihar | F4: Gaya | G4: Electronics | H4: Laptop | I4: 3 | J4: 424.77 | K4: =J4*I4 -> 1274.31 | L4: 1577.15 | M4: =L4-K4 -> 302.84 | N4: Low | O4: Cash
A5: ORD04 | B5: 45296 | C5: Customer_160 | D5: North | E5: Uttar Pradesh | F5: Prayagraj | G5: Electronics | H5: Tablet | I5: 8 | J5: 326.62 | K5: =J5*I5 -> 2612.96 | L5: 3634.92 | M5: =L5-K5 -> 1021.96 | N5: High | O5: UPI
A6: ORD05 | B6: 45297 | C6: Customer_68 | D6: South | E6: Tamil Nadu | F6: Tiruchirappalli | G6: Electronics | H6: Laptop | I6: 10 | J6: 367.76 | K6: =J6*I6 -> 3677.6 | L6: 4155.22 | M6: =L6-K6 -> 477.62 | N6: High | O6: Cash
A7: ORD06 | B7: 45298 | C7: Customer_163 | D7: Northeast | E7: Assam | F7: Guwahati | G7: Electronics | H7: Mobile | I7: 7 | J7: 409.03 | K7: =J7*I7 -> 2863.21 | L7: 4274.21 | M7: =L7-K7 -> 1411 | N7: High | O7: Cash
A8: ORD07 | B8: 45299 | C8: Customer_33 | D8: West | E8: Maharashtra | F8: Mumbai | G8: Electronics | H8: Mobile | I8: 10 | J8: 368.99 | K8: =J8*I8 -> 3689.9 | L8: 5125.56 | M8: =L8-K8 -> 1435.66 | N8: High | O8: UPI
A9: ORD08 | B9: 45300 | C9: Customer_124 | D9: East | E9: West Bengal | F9: Howrah | G9: Electronics | H9: Tablet | I9: 1 | J9: 426.59 | K9: =J9*I9 -> 426.59 | L9: 481.05 | M9: =L9-K9 -> 54.46 | N9: Low | O9: UPI
A10: ORD09 | B10: 45301 | C10: Customer_79 | D10: West | E10: Maharashtra | F10: Aurangabad | G10: Electronics | H10: Accessories | I10: 9 | J10: 91.86 | K10: =J10*I10 -> 826.74 | L10: 941.24 | M10: =L10-K10 -> 114.5 | N10: Low | O10: Cash
A11: ORD10 | B11: 45302 | C11: Customer_159 | D11: East | E11: West Bengal | F11: Asansol | G11: Electronics | H11: Tablet | I11: 6 | J11: 248.87 | K11: =J11*I11 -> 1493.22 | L11: 2161.96 | M11: =L11-K11 -> 668.74 | N11: High | O11: Card
A12: ORD11 | B12: 45303 | C12: Customer_45 | D12: Northeast | E12: Assam | F12: Dibrugarh | G12: Electronics | H12: Accessories | I12: 8 | J12: 242.76 | K12: =J12*I12 -> 1942.08 | L12: 2301.16 | M12: =L12-K12 -> 359.08 | N12: High | O12: UPI
A13: ORD12 | B13: 45304 | C13: Customer_95 | D13: East | E13: Jharkhand | F13: Hazaribagh | G13: Electronics | H13: Tablet | I13: 7 | J13: 171.73 | K13: =J13*I13 -> 1202.11 | L13: 1471.92 | M13: =L13-K13 -> 269.81 | N13: Low | O13: UPI
A14: ORD13 | B14: 45305 | C14: Customer_185 | D14: North | E14: Madhya Pradesh | F14: Bhopal | G14: Electronics | H14: Tablet | I14: 4 | J14: 359.8 | K14: =J14*I14 -> 1439.2 | L14: 1645.82 | M14: =L14-K14 -> 206.62 | N14: Low | O14: Cash
... A1001: ORD1000 | B1001: 46292 | C1001: Customer_45 | D1001: North | E1001: Madhya Pradesh | F1001: Howrah | G1001: Electronics | H1001: Mobile | I1001: 9 | J1001: 445.16 | K1001: =J1001*I1001 -> 4006.44 | L1001: 4813.18 | M1001: =L1001-K1001 -> 806.74 | N1001: High | O1001: Cash

Sheet Vlookup & Xlookup 
B3: Vlookup & Xlookup
B4: Order ID | C4: Customer Name | D4: Region | E4: Profit | F4: Payment mode
B5: ORD28 | C5: =VLOOKUP(B5,Salestable,3,0) -> Customer_102 | D5: =VLOOKUP($B$5,Salestable,4,0) -> South | E5: =VLOOKUP($B$5,Salestable,13,0) -> 287.55 | F5: =VLOOKUP($B$5,Salestable,15,0) -> UPI
B6: ORD202 | C6: =_xlfn.XLOOKUP($B$6,'Sales Data'!$A:$A,'Sales Data'!C:C) -> Customer_76 | D6: =_xlfn.XLOOKUP($B$6,'Sales Data'!$A:$A,'Sales Data'!D:D) -> North | E6: =_xlfn.XLOOKUP(B6,'Sales Data'!A1:A1001,'Sales Data'!M1:M1001) -> 18.06 | F6: =_xlfn.XLOOKUP($B$6,'Sales Data'!$A:$A,'Sales Data'!F:F) -> Prayagraj

Sheet KPI Summary
A1: KPI | B1: Value
A2: Total Cost | B2: =SUM('Sales Data'!K2:K1001) -> 1471485.9
A3: Total Sales | B3: =SUM('Sales Data'!L2:L1001) -> 1908865.6
A4: Total Profit | B4: =SUM('Sales Data'!M2:M1001) -> 437379.68 | S4: =_xlfn.XLOOKUP(P4,A1:A1001,M1:M1001) -> 0
A5: Total orders | B5: =COUNTA('Sales Data'!A2:A1001) -> 1000
A6: Avg Profit | B6: =AVERAGE('Sales Data'!M2:M1001) -> 437.37968
A8: Analysis
A9: Region | B9: Sales | C9: Profit | E9: Product | F9: Sales | G9: Profit | I9: Payment Mode | J9: Values
A10: North | B10: =SUMIF('Sales Data'!D2:D1001,'KPI Summary'!A10,'Sales Data'!L2:L1001) -> 633941.5 | C10: =SUMIF('Sales Data'!D2:D1001,'KPI Summary'!A10,'Sales Data'!M2:M1001) -> 145015.59 | E10: Laptop | F10: =SUMIF('Sales Data'!H2:H1001,'KPI Summary'!E10,'Sales Data'!L2:L1001) -> 536622.58 | G10: =SUMIF('Sales Data'!H2:H1001,'KPI Summary'!E10,'Sales Data'!M2:M1001) -> 120707.43 | I10: UPI | J10: =COUNTIF('Sales Data'!O2:O1001,'KPI Summary'!I10) -> 332
A11: Northeast | B11: =SUMIF('Sales Data'!D3:D1002,'KPI Summary'!A11,'Sales Data'!L3:L1002) -> 110443.25 | C11: =SUMIF('Sales Data'!D3:D1002,'KPI Summary'!A11,'Sales Data'!M3:M1002) -> 24976.02 | E11: Mobile | F11: =SUMIF('Sales Data'!H3:H1002,'KPI Summary'!E11,'Sales Data'!L3:L1002) -> 392010.39 | G11: =SUMIF('Sales Data'!H3:H1002,'KPI Summary'!E11,'Sales Data'!M3:M1002) -> 91474.67 | I11: Cash | J11: =COUNTIF('Sales Data'!O3:O1002,'KPI Summary'!I11) -> 338
A12: South | B12: =SUMIF('Sales Data'!D3:D1002,'KPI Summary'!A12,'Sales Data'!L3:L1002) -> 340459.56 | C12: =SUMIF('Sales Data'!D3:D1002,'KPI Summary'!A12,'Sales Data'!M3:M1002) -> 78610.12 | E12: Tablet | F12: =SUMIF('Sales Data'!H4:H1003,'KPI Summary'!E12,'Sales Data'!L4:L1003) -> 540068.69 | G12: =SUMIF('Sales Data'!H4:H1003,'KPI Summary'!E12,'Sales Data'!M4:M1003) -> 122762.07 | I12: Card | J12: =COUNTIF('Sales Data'!O4:O1003,'KPI Summary'!I12) -> 330
A13: East | B13: =SUMIF('Sales Data'!D4:D1003,'KPI Summary'!A13,'Sales Data'!L4:L1003) -> 488554.02 | C13: =SUMIF('Sales Data'!D4:D1003,'KPI Summary'!A13,'Sales Data'!M4:M1003) -> 114855.67 | E13: Accessories | F13: =SUMIF('Sales Data'!H5:H1004,'KPI Summary'!E13,'Sales Data'!L5:L1004) -> 435966.42 | G13: =SUMIF('Sales Data'!H5:H1004,'KPI Summary'!E13,'Sales Data'!M5:M1004) -> 101789.45
A14: West | B14: =SUMIF('Sales Data'!D5:D1004,'KPI Summary'!A14,'Sales Data'!L5:L1004) -> 330654.07 | C14: =SUMIF('Sales Data'!D5:D1004,'KPI Summary'!A14,'Sales Data'!M5:M1004) -> 73115.54
A15: Total | B15: =SUM(B10:B14) -> 1904052.4 | C15: =SUM(C10:C14) -> 436572.94 | E15: Total | F15: =SUM(F10:F13) -> 1904668.1 | G15: =SUM(G10:G13) -> 436733.62 | I15: Total | J15: =SUM(J10:J12) -> 1000

Sheet Pivot Table
A3: Sum of Profit | B3: Column Labels | H3: Sum of Sales Amount | J3: Sum of Profit
A4: Row Labels | B4: Accessories | C4: Laptop | D4: Mobile | E4: Tablet | F4: Grand Total | H4: 1908865.6 | J4: 437379.68
A5: 2024 | B5: 38605.8 | C5: 41604.96 | D5: 33107.93 | E5: 48862.57 | F5: 162181.26
A6: 2025 | B6: 35073.43 | C6: 47519.94 | D6: 33836.04 | E6: 44050.03 | F6: 160479.44 | H6: =GETPIVOTDATA("Sales Amount",$H$3) -> 1908865.6 | J6: =GETPIVOTDATA("Profit",$J$3) -> 437379.68
A7: 2026 | B7: 28646.41 | C7: 31582.53 | D7: 24530.7 | E7: 29959.34 | F7: 114718.98
A8: Grand Total | B8: 102325.64 | C8: 120707.43 | D8: 91474.67 | E8: 122871.94 | F8: 437379.68
A12: Row Labels | B12: Sum of Sales Amount | D12: Row Labels | E12: Count of Customer Name | G12: Row Labels | H12: Count of Product
A13: East | B13: 488554.02 | D13: 2024 | E13: 365 | G13: Card | H13: 330
A14: North | B14: 633941.5 | D14: 2025 | E14: 365 | G14: Cash | H14: 338
A15: North | B15: 4813.18 | D15: 2026 | E15: 270 | G15: UPI | H15: 332
A16: Northeast | B16: 110443.25 | D16: Grand Total | E16: 1000 | G16: Grand Total | H16: 1000
A17: South | B17: 340459.56
A18: West | B18: 330654.07
A19: Grand Total | B19: 1908865.6
A22: Row Labels | B22: Sum of Profit | D22: Row Labels | E22: Sum of Sales Amount
A23: Accessories | B23: 102325.64 | D23: Accessories | E23: 439406.05
A24: Laptop | B24: 120707.43 | D24: Laptop | E24: 536622.58
A25: Mobile | B25: 91474.67 | D25: Mobile | E25: 392010.39
A26: Tablet | B26: 122871.94 | D26: Tablet | E26: 540826.56
A27: Grand Total | B27: 437379.68 | D27: Grand Total | E27: 1908865.6

Sheet Dashboard

Sheet Business Insigts
B2: Business Insights
B3: 1. Identified top 3 regions contributing 60% of revenue and highlighted loss-making categories, improving decision-making
B4: 2. Tablet shows highest profit margin among all products.
B5: 3. Cash payment method accounts for the majority of transactions, indicating customer preference.
B6: 4. Electronics category most profitable.
